yabmp/__init__.py
yabmp/config.py
yabmp/hooks.py
yabmp/log.py
yabmp/service.py
yabmp/channel/__init__.py
yabmp/channel/config.py
yabmp/channel/consumer.py
yabmp/channel/factory.py
yabmp/channel/protocol.py
yabmp/channel/publisher.py
yabmp/cmd/__init__.py
yabmp/common/__init__.py
yabmp/common/constants.py
yabmp/common/exception.py
yabmp/core/__init__.py
yabmp/core/factory.py
yabmp/core/protocol.py
yabmp/handler/__init__.py
yabmp/handler/default.py
yabmp/message/__init__.py
yabmp/message/bmp.py
yabmp/tests/__init__.py
yabmp-0.2.0.data/data/etc/yabmp/yabmp.ini/yabmp.ini.sample
yabmp-0.2.0.dist-info/DESCRIPTION.rst
yabmp-0.2.0.dist-info/entry_points.txt
yabmp-0.2.0.dist-info/METADATA
yabmp-0.2.0.dist-info/metadata.json
yabmp-0.2.0.dist-info/pbr.json
yabmp-0.2.0.dist-info/RECORD
yabmp-0.2.0.dist-info/top_level.txt
yabmp-0.2.0.dist-info/WHEEL
