Metadata-Version: 2.0
Name: yabmp
Version: 0.2.0
Summary: A Python BMP Receiver
Home-page: http://smartbgp.github.io/
Author: SmartBGP project team
Author-email: penxiao@cisco.com
License: Apache License 2.0
Keywords: BGP
Requires-Dist: yabgp
Requires-Dist: netaddr (>=0.7.12)
Requires-Dist: pbr (==2.0.0)
Requires-Dist: oslo.config (==2.1.0)
Requires-Dist: Twisted (==16.0.0)
Requires-Dist: bitstring (==3.1.5)
Requires-Dist: six (==1.10.0)
Requires-Dist: pika (==0.9.14)
